rlottie_python/__init__.py
rlottie_python/_rlottiecommon.py
rlottie_python/py.typed
rlottie_python/rlottie.dll
rlottie_python/rlottie_wrapper.py
rlottie_python-1.3.8.dist-info/LICENSE
rlottie_python-1.3.8.dist-info/METADATA
rlottie_python-1.3.8.dist-info/WHEEL
rlottie_python-1.3.8.dist-info/entry_points.txt
rlottie_python-1.3.8.dist-info/RECORD
