Metadata-Version: 2.1
Name: rlottie-python
Version: 1.3.8
Summary: A ctypes API for rlottie, with additional functions for getting Pillow Image.
Keywords: rlottie lottie tgs ctypes
Author-Email: chaudominic <chaudominic2@gmail.com>
License:                   GNU LESSER GENERAL PUBLIC LICENSE
Classifier: Topic :: Multimedia :: Graphics
Project-URL: Repository, https://github.com/laggykiller/rlottie-python
Project-URL: Documentation, https://rlottie-python.readthedocs.io/en/latest/
Project-URL: Tracker, https://github.com/laggykiller/rlottie-python/issues
Requires-Python: >=3.7
Provides-Extra: full
Provides-Extra: test
Provides-Extra: lint
Requires-Dist: Pillow; extra == "full"
Requires-Dist: pytest; extra == "test"
Requires-Dist: ruff; extra == "lint"
Requires-Dist: mypy; extra == "lint"
Requires-Dist: isort; extra == "lint"
Requires-Dist: types-Pillow; extra == "lint"
